flask_auth/__init__.py
flask_auth/base.py
flask_auth/decorators.py
flask_auth/fields.py
flask_auth/forms.py
flask_auth/models.py
flask_auth/validators.py
flask_aa-0.1.0.dist-info/LICENSE
flask_aa-0.1.0.dist-info/METADATA
flask_aa-0.1.0.dist-info/WHEEL
flask_aa-0.1.0.dist-info/RECORD
